{
  "items": [
    {
      "id": "19ae9b10ba5253d0",
      "subject": "NYMS pop-up walk, Long Pond Park, Staten Island, Sunday, December 7th",
      "date": "2025-12-04T09:09:07-05:00",
      "snippet": "Plus... a SALE on T-Shirts; NAMA Fungus Film Fest; Fun With Fungi book event <https://www.newyorkmyc.org?mailpoet_router&endpoint=track&action=click&data=WyIzNzIzIiwiYzE3NzVjIiwiMzMyIiwiZjYxY2FmNDM1ZDNjIixmYWxzZV0> Thursday December 4th, 2025 *NYMS pop-up walk",
      "from": "BasidiomyCody <basidiomycody@gmail.com>",
      "tags": [
        "news"
      ]
    },
    {
      "id": "19ae7b9bf0cc808c",
      "subject": "Testing",
      "date": "2025-12-03T23:58:05-05:00",
      "snippet": "Testingtestingtesting test",
      "from": "Agaricus Bisporus <comm.hub.myco@gmail.com>",
      "tags": [
        "news"
      ]
    },
    {
      "id": "19ac3abab4690697",
      "subject": "Re: [BasidiomyCody/champ-site] Adding Cloudflare worker (PR #1)",
      "date": "2025-11-26T23:56:38-05:00",
      "snippet": "@comm-hub-myco pushed 1 commit. 3c7c9fa6f1609cd5d5ce79cba1cacccbf5ff5737 Update style.css -- View it on GitHub: https://github.com/BasidiomyCody/champ-site/pull/1/files/f872d72c32838c12652abf0e1dee8fadae3862a1..3c7c9fa6f1609cd5d5ce79cba1cacccbf5ff5737 You are ",
      "from": "comm-hub-myco <notifications@github.com>",
      "tags": [
        "news"
      ]
    }
  ]
}